{
  "version": 3,
  "projects": {},
  "selectedDraftVaultPath": "Personal/Writing/Stories/Short Stories/The Survivalist/Index.md",
  "userScriptFolder": null,
  "sessionStorage": "data",
  "sessions": [
    {
      "start": "2026-02-01T02:34:02.109Z",
      "total": 0,
      "drafts": {
        "Personal/Writing/Stories/The Survivalist/Index.md": {
          "total": 0,
          "scenes": {}
        },
        "Personal/Writing/Stories/Short Stories/The Survivalist/Index.md": {
          "total": 0,
          "scenes": {}
        }
      }
    },
    {
      "start": "2026-01-26T01:48:11.910Z",
      "total": 0,
      "drafts": {
        "Personal/Writing/Stories/The Survivalist/Index.md": {
          "total": 0,
          "scenes": {}
        }
      }
    },
    {
      "start": "2026-01-24T02:12:58.052Z",
      "total": 0,
      "drafts": {
        "Personal/Writing/Stories/The Survivalist/Index.md": {
          "total": 0,
          "scenes": {}
        }
      }
    },
    {
      "start": "2026-01-18T15:34:57.971Z",
      "total": 0,
      "drafts": {
        "Personal/Writing/Stories/The Survivalist/Index.md": {
          "total": 0,
          "scenes": {}
        }
      }
    },
    {
      "start": "2026-01-16T12:06:32.715Z",
      "total": 0,
      "drafts": {
        "Personal/Writing/Stories/The Survivalist/Index.md": {
          "total": 0,
          "scenes": {}
        }
      }
    },
    {
      "start": "2026-01-15T13:42:55.385Z",
      "total": 0,
      "drafts": {
        "Personal/Writing/Stories/The Survivalist/Index.md": {
          "total": 0,
          "scenes": {}
        }
      }
    },
    {
      "start": "2026-01-14T13:07:05.180Z",
      "total": 0,
      "drafts": {
        "Personal/Writing/Stories/The Survivalist/Index.md": {
          "total": 0,
          "scenes": {}
        }
      }
    },
    {
      "start": "2026-01-03T18:11:11.721Z",
      "total": 0,
      "drafts": {
        "Personal/Writing/Stories/The Survivalist/Index.md": {
          "total": 0,
          "scenes": {}
        }
      }
    },
    {
      "start": "2026-01-02T22:51:17.193Z",
      "total": 0,
      "drafts": {
        "Personal/Writing/Stories/The Survivalist/Index.md": {
          "total": 0,
          "scenes": {}
        }
      }
    },
    {
      "start": "2025-12-30T15:46:56.627Z",
      "total": 0,
      "drafts": {
        "Personal/Writing/Stories/The Survivalist/Index.md": {
          "total": 0,
          "scenes": {}
        }
      }
    },
    {
      "start": "2025-12-29T20:39:22.562Z",
      "total": 0,
      "drafts": {
        "Personal/Writing/Stories/The Survivalist/Index.md": {
          "total": 0,
          "scenes": {}
        }
      }
    },
    {
      "start": "2025-12-27T14:20:11.742Z",
      "total": 0,
      "drafts": {
        "Personal/Writing/Stories/The Survivalist/Index.md": {
          "total": 0,
          "scenes": {}
        }
      }
    },
    {
      "start": "2025-12-21T17:56:00.552Z",
      "total": 0,
      "drafts": {
        "Personal/Writing/Stories/The Survivalist/Index.md": {
          "total": 0,
          "scenes": {}
        }
      }
    },
    {
      "start": "2025-12-20T15:54:38.138Z",
      "total": 0,
      "drafts": {
        "Personal/Writing/Stories/The Survivalist/Index.md": {
          "total": 0,
          "scenes": {}
        }
      }
    },
    {
      "start": "2025-12-19T16:42:51.470Z",
      "total": 0,
      "drafts": {
        "Personal/Writing/Stories/The Survivalist/Index.md": {
          "total": 0,
          "scenes": {}
        }
      }
    },
    {
      "start": "2025-12-12T13:51:02.996Z",
      "total": 0,
      "drafts": {
        "Personal/Writing/Stories/The Survivalist/Index.md": {
          "total": 0,
          "scenes": {}
        }
      }
    },
    {
      "start": "2025-12-08T22:09:09.972Z",
      "total": 0,
      "drafts": {
        "Personal/Writing/Stories/The Survivalist/Index.md": {
          "total": 0,
          "scenes": {}
        }
      }
    },
    {
      "start": "2025-12-08T01:30:13.888Z",
      "total": 0,
      "drafts": {
        "Personal/Writing/Stories/The Survivalist/Index.md": {
          "total": 0,
          "scenes": {}
        }
      }
    },
    {
      "start": "2025-12-02T17:59:01.028Z",
      "total": 0,
      "drafts": {
        "Personal/Writing/Stories/The Survivalist/Index.md": {
          "total": 0,
          "scenes": {}
        }
      }
    },
    {
      "start": "2025-12-01T09:34:15.060Z",
      "total": 0,
      "drafts": {
        "Personal/Writing/Stories/The Survivalist/Index.md": {
          "total": 0,
          "scenes": {}
        }
      }
    },
    {
      "start": "2025-11-21T20:06:32.213Z",
      "total": 0,
      "drafts": {
        "Personal/Writing/Stories/The Survivalist/Index.md": {
          "total": 0,
          "scenes": {}
        }
      }
    },
    {
      "start": "2025-11-20T15:55:35.958Z",
      "total": 0,
      "drafts": {
        "Personal/Writing/Stories/The Survivalist/Index.md": {
          "total": 0,
          "scenes": {}
        }
      }
    },
    {
      "start": "2025-11-15T13:24:09.295Z",
      "total": 0,
      "drafts": {
        "Personal/Writing/Stories/The Survivalist/Index.md": {
          "total": 0,
          "scenes": {}
        }
      }
    },
    {
      "start": "2025-11-13T20:05:47.327Z",
      "total": 0,
      "drafts": {
        "Personal/Writing/Stories/The Survivalist/Index.md": {
          "total": 0,
          "scenes": {}
        }
      }
    },
    {
      "start": "2025-11-12T12:17:21.477Z",
      "total": 0,
      "drafts": {
        "Personal/Writing/Stories/The Survivalist/Index.md": {
          "total": 0,
          "scenes": {}
        }
      }
    },
    {
      "start": "2025-11-11T21:46:14.527Z",
      "total": 0,
      "drafts": {
        "Personal/Writing/Stories/The Survivalist/Index.md": {
          "total": 0,
          "scenes": {}
        }
      }
    },
    {
      "start": "2025-11-09T14:00:20.849Z",
      "total": 0,
      "drafts": {
        "Personal/Writing/Stories/The Survivalist/Index.md": {
          "total": 0,
          "scenes": {}
        }
      }
    },
    {
      "start": "2025-11-03T13:28:28.865Z",
      "total": 0,
      "drafts": {
        "Personal/Writing/Stories/The Survivalist/Index.md": {
          "total": 0,
          "scenes": {}
        }
      }
    },
    {
      "start": "2025-10-31T12:00:39.986Z",
      "total": 0,
      "drafts": {
        "Personal/Writing/Stories/The Survivalist/Index.md": {
          "total": 0,
          "scenes": {}
        }
      }
    },
    {
      "start": "2025-10-28T12:36:21.671Z",
      "total": 0,
      "drafts": {
        "Personal/Writing/Stories/The Survivalist/Index.md": {
          "total": 0,
          "scenes": {}
        }
      }
    }
  ],
  "showWordCountInStatusBar": true,
  "startNewSessionEachDay": true,
  "sessionGoal": 500,
  "applyGoalTo": "all",
  "notifyOnGoal": true,
  "countDeletionsForGoal": false,
  "keepSessionCount": 30,
  "sessionFile": "longform-sessions.json",
  "numberScenes": false,
  "sceneTemplate": null,
  "waitForSync": false,
  "fallbackWaitEnabled": true,
  "fallbackWaitTime": 5,
  "workflows": {
    "Default Workflow": {
      "name": "Default Workflow",
      "description": "A starter workflow. Feel free to edit, rename, or delete it and create your own.",
      "steps": [
        {
          "id": "strip-frontmatter",
          "optionValues": {}
        },
        {
          "id": "remove-links",
          "optionValues": {
            "remove-wikilinks": true,
            "remove-external-links": true
          }
        },
        {
          "id": "prepend-title",
          "optionValues": {
            "format": "$3{#} $1",
            "separator": "\n\n"
          }
        },
        {
          "id": "concatenate-text",
          "optionValues": {
            "separator": "\\n\\n---\\n\\n"
          }
        },
        {
          "id": "write-to-note",
          "optionValues": {
            "target": "manuscript.md",
            "open-after": true
          }
        }
      ]
    }
  }
}